{
  "common_themes": [
    "Нестабильность переводов и операций",
    "Медленная и неэффективная поддержка",
    "Проблемы с производительностью приложения",
    "Отсутствие шаблонов для частых платежей",
    "Задержки уведомлений",
    "Нестабильная биометрия"
  ],
  "unique_per_bank": {
    "dom_bank": [
      "Лаги в пиковые часы",
      "Невозможность прикрепить несколько файлов к платежу",
      "После обновления приложение тормозит и вылетает при просмотре истории"
    ],
    "polus_bank": [
      "Навязчивые уведомления с рекламой",
      "Жёсткая верификация при смене устройства",
      "Не хватает рыночной аналитики и интеграции с налоговой"
    ],
    "sfera_bank": [
      "После обновлений исчезает история",
      "Лимиты на переводы не синхронизированы с веб-версией",
      "Сканер чеков через камеру не распознаёт данные"
    ],
    "strela_bank": [
      "Отсутствие тёмной темы и мелкий шрифт",
      "Пользователи сравнивают с Альфа-Банком и Тинькофф",
      "Хотели бы привязку нескольких карт и больше категорий для кэшбэка"
    ],
    "vector_bank": [
      "Навязчивая реклама кредитов и страховок",
      "Пользователям нравится история операций и категории трат",
      "Пополнение карт без комиссии и заказ справок"
    ]
  },
  "overall_headline": "Пользователи ценят скорость переводов и дизайн, но стабильность, поддержка и функциональность требуют значительных улучшений"
}